arlas_api_python/__init__.py
arlas_api_python/api_client.py
arlas_api_python/configuration.py
arlas_api_python/rest.py
arlas_api_python/api/__init__.py
arlas_api_python/api/collections_api.py
arlas_api_python/api/explore_api.py
arlas_api_python/models/__init__.py
arlas_api_python/models/aggregation.py
arlas_api_python/models/aggregation_metric.py
arlas_api_python/models/aggregation_response.py
arlas_api_python/models/aggregations_request.py
arlas_api_python/models/arlas_hit.py
arlas_api_python/models/bbox.py
arlas_api_python/models/collection_display_names.py
arlas_api_python/models/collection_organisations.py
arlas_api_python/models/collection_reference.py
arlas_api_python/models/collection_reference_description.py
arlas_api_python/models/collection_reference_description_property.py
arlas_api_python/models/collection_reference_parameters.py
arlas_api_python/models/computation_request.py
arlas_api_python/models/computation_response.py
arlas_api_python/models/count.py
arlas_api_python/models/crs.py
arlas_api_python/models/dublin_core_element_name.py
arlas_api_python/models/error.py
arlas_api_python/models/expression.py
arlas_api_python/models/feature.py
arlas_api_python/models/feature_collection.py
arlas_api_python/models/feed.py
arlas_api_python/models/filter.py
arlas_api_python/models/form.py
arlas_api_python/models/generator.py
arlas_api_python/models/geo.py
arlas_api_python/models/geo_json_object.py
arlas_api_python/models/geometry_collection.py
arlas_api_python/models/hits.py
arlas_api_python/models/hits_fetcher.py
arlas_api_python/models/inspire.py
arlas_api_python/models/inspire_limitation_access.py
arlas_api_python/models/inspire_spatial_resolution.py
arlas_api_python/models/inspire_uri.py
arlas_api_python/models/interval.py
arlas_api_python/models/keyword.py
arlas_api_python/models/line_string.py
arlas_api_python/models/link.py
arlas_api_python/models/lng_lat_alt.py
arlas_api_python/models/md.py
arlas_api_python/models/metric.py
arlas_api-24.1.0.dist-info/METADATA
arlas_api-24.1.0.dist-info/WHEEL
arlas_api-24.1.0.dist-info/top_level.txt
arlas_api-24.1.0.dist-info/RECORD
