Metadata-Version: 2.1
Name: arlas-api
Version: 24.1.0
Summary: ARLAS Exploration API
Home-page: https://github.com/gisaia/ARLAS-server
Author: Gisaïa
Author-email: contact@gisaia.com
License: UNKNOWN
Keywords: Arlas,ARLAS Exploration API
Platform: UNKNOWN
Requires-Dist: urllib3 (>=1.15)
Requires-Dist: six (>=1.10)
Requires-Dist: certifi
Requires-Dist: python-dateutil
